Workbook
Name Aporte: Controle_Investimento!$F$14
Name dividendo: Controle_Investimento!$F$18
Name patrimonio_Ac: Controle_Investimento!$F$17
Name QTD_Anos: Controle_Investimento!$F$15
Name Rendiemento_Carteira: Controle_Investimento!$F$10
Name salario: Controle_Investimento!$F$9
Name sugestao_invest: Controle_Investimento!$F$11
Name Taxa_Mensal: Controle_Investimento!$F$16

Sheet Controle_Investimento
D8: ORIGEM DO INVESTIMENTO
D9: Salário | F9: 5480
D10: Rendimento da Carteira | F10: 0.0085
D11: Sugestão de investimento (30%) | F11: =F9*30% -> 1644
D13: INVESTIMENTO MENSASL
D14: Quanto investir por mês? | F14: =sugestao_invest -> 1644
D15: Por quantos anos? | F15: 5
D16: Taxa de Rendimentos mensal? | F16: 0.01079
D17: Patrimônio acumulado? | F17: =FV(F16,F15*12,F14)*(-1) -> 137729.25
D18: Dividendos mensais? | F18: =F17*F10 -> 1170.6986
D20: CENARIOS | E20: Patrimônio Acumulado | F20: Dividendo
C21: 2 | D21: Quanto em 2 Anos ? | E21: =FV($F$16,$C21*12,$F$14)*-1 -> 44762.219 | F21: =E21*$F$10 -> 380.47886
C22: 5 | D22: Quanto em 5 Anos ? | E22: =FV($F$16,$C22*12,$F$14)*-1 -> 137729.25 | F22: =E22*$F$10 -> 1170.6986
C23: 10 | D23: Quanto em 10 Anos ? | E23: =FV($F$16,$C23*12,$F$14)*-1 -> 399959.25 | F23: =E23*$F$10 -> 3399.6536
C24: 20 | D24: Quanto em 20 Anos ? | E24: =FV($F$16,$C24*12,$F$14)*-1 -> 1849826.2 | F24: =E24*$F$10 -> 15723.522
C25: 30 | D25: Quanto em 30 Anos ? | E25: =FV($F$16,$C25*12,$F$14)*-1 -> 7105646.9 | F25: =E25*$F$10 -> 60397.999
D27: PERFIL | F27: Conservador
D28: Valor a ser investidos por mês | F28: =sugestao_invest -> 1644
D30: TIPO DE FII | E30: Percentual Sugerido | F30: Valores
D31: PAPEL | E31: =VLOOKUP($F$27&"-"&D31,Planilha1!$A$2:$D$20,4,FALSE) -> 0.25 | F31: =$F$28*E31 -> 411
D32: TIJOLO | E32: =VLOOKUP($F$27&"-"&D32,Planilha1!$A$2:$D$20,4,FALSE) -> 0.3 | F32: =$F$28*E32 -> 493.2
D33: HIBRIDOS | E33: =VLOOKUP($F$27&"-"&D33,Planilha1!$A$2:$D$20,4,FALSE) -> 0.15 | F33: =$F$28*E33 -> 246.6
D34: FOFS | E34: =VLOOKUP($F$27&"-"&D34,Planilha1!$A$2:$D$20,4,FALSE) -> 0.1 | F34: =$F$28*E34 -> 164.4
D35: DESENVOLVIMENTO | E35: =VLOOKUP($F$27&"-"&D35,Planilha1!$A$2:$D$20,4,FALSE) -> 0.12 | F35: =$F$28*E35 -> 197.28
D36: HOTELARIA | E36: =VLOOKUP($F$27&"-"&D36,Planilha1!$A$2:$D$20,4,FALSE) -> 0.08 | F36: =$F$28*E36 -> 131.52
F37: =SUM(F31:F36) -> 1644

Sheet Planilha1
A2: CHAVE | B2: PERFIL | C2: TIPO DE FII | D2: %
A3: =B3&"-"&C3 -> Moderado-PAPEL | B3: Moderado | C3: PAPEL | D3: 0.35
A4: =B4&"-"&C4 -> Moderado-TIJOLO | B4: Moderado | C4: TIJOLO | D4: 0.35
A5: =B5&"-"&C5 -> Moderado-HIBRIDOS | B5: Moderado | C5: HIBRIDOS | D5: 0.15
A6: =B6&"-"&C6 -> Moderado-FOFS | B6: Moderado | C6: FOFS | D6: 0.1
A7: =B7&"-"&C7 -> Moderado-DESENVOLVIMENTO | B7: Moderado | C7: DESENVOLVIMENTO | D7: 0.03
A8: =B8&"-"&C8 -> Moderado-HOTELARIA | B8: Moderado | C8: HOTELARIA | D8: 0.02
A9: =B9&"-"&C9 -> Conservador-PAPEL | B9: Conservador | C9: PAPEL | D9: 0.25
A10: =B10&"-"&C10 -> Conservador-TIJOLO | B10: Conservador | C10: TIJOLO | D10: 0.3
A11: =B11&"-"&C11 -> Conservador-HIBRIDOS | B11: Conservador | C11: HIBRIDOS | D11: 0.15
A12: =B12&"-"&C12 -> Conservador-FOFS | B12: Conservador | C12: FOFS | D12: 0.1
A13: =B13&"-"&C13 -> Conservador-DESENVOLVIMENTO | B13: Conservador | C13: DESENVOLVIMENTO | D13: 0.12
A14: =B14&"-"&C14 -> Conservador-HOTELARIA | B14: Conservador | C14: HOTELARIA | D14: 0.08
... A20: =B20&"-"&C20 -> Agressivo-HOTELARIA | B20: Agressivo | C20: HOTELARIA | D20: 0.1

Sheet Planilha2
